Metadata-Version: 2.1
Name: PyConvertBinary
Version: 0.0.5
Summary: Basic Binary Converter
Home-page: 
Author: R3Pulse
Author-email: adrain911@gmail.com
License: MIT
Keywords: converter,binary,decimal
Classifier: Development Status :: 5 - Production/Stable
Classifier: Intended Audience :: Education
Classifier: Operating System :: Microsoft :: Windows :: Windows 10
Classifier: License :: OSI Approved :: MIT License
Classifier: Programming Language :: Python :: 3.9
License-File: LICENSE.txt
